yolo_health_checker/__init__.py
yolo_health_checker/analyze_dataset.py
yolo_health_checker-0.1.1.dist-info/METADATA
yolo_health_checker-0.1.1.dist-info/WHEEL
yolo_health_checker-0.1.1.dist-info/top_level.txt
yolo_health_checker-0.1.1.dist-info/RECORD
