Metadata-Version: 2.1
Name: yolo-health-checker
Version: 0.1.1
Summary: A tool to numerically analyze the health of a YOLO dataset.
Author-email: Rodrigo Ferraz Souza <dev.rodrigofs@gmail.com>
Project-URL: Source Code, https://github.com/CodeWracker/yolo-health-checker
Project-URL: Bug Tracker, https://github.com/CodeWracker/yolo-health-checker/issues
Keywords: yolo,dataset,analysis
Classifier: Programming Language :: Python :: 3
Classifier: Operating System :: OS Independent
Requires-Dist: pyyaml
Requires-Dist: numpy
Requires-Dist: matplotlib
Requires-Dist: pandas
Requires-Dist: tqdm
